Workbook

Sheet Dashboard
A1: DASHBOARD DE VENDAS - DISTRIBUIÇÃO DE VENTILADORES
B4: FATURAMENTO TOTAL | E4: TOTAL UNIDADES VENDIDAS | H4: LUCRO LÍQUIDO TOTAL
B5: =SUM('Dados de Vendas'!H2:H151) -> 237179.7 | E5: =SUM('Dados de Vendas'!G2:G151) -> 1203 | H5: =SUM('Dados de Vendas'!J2:J151) -> 124146.7
B8: Faturamento por Canal | E8: Faturamento por Região
B9: Canal | C9: Faturamento | E9: Região | F9: Faturamento
B10: E-commerce | C10: =SUMIF('Dados de Vendas'!C$2:C$151, B10, 'Dados de Vendas'!H$2:H$151) -> 40527.3 | E10: Sudeste | F10: =SUMIF('Dados de Vendas'!D$2:D$151, E10, 'Dados de Vendas'!H$2:H$151) -> 33430.1
B11: Lojas Físicas | C11: =SUMIF('Dados de Vendas'!C$2:C$151, B11, 'Dados de Vendas'!H$2:H$151) -> 65317.4 | E11: Nordeste | F11: =SUMIF('Dados de Vendas'!D$2:D$151, E11, 'Dados de Vendas'!H$2:H$151) -> 43828
B12: Marketplace | C12: =SUMIF('Dados de Vendas'!C$2:C$151, B12, 'Dados de Vendas'!H$2:H$151) -> 81059.2 | E12: Sul | F12: =SUMIF('Dados de Vendas'!D$2:D$151, E12, 'Dados de Vendas'!H$2:H$151) -> 36482.4
B13: Televendas | C13: =SUMIF('Dados de Vendas'!C$2:C$151, B13, 'Dados de Vendas'!H$2:H$151) -> 50275.8 | E13: Centro-Oeste | F13: =SUMIF('Dados de Vendas'!D$2:D$151, E13, 'Dados de Vendas'!H$2:H$151) -> 56570.8
B14: Total | C14: =SUM(C10:C13) -> 237179.7 | E14: Norte | F14: =SUMIF('Dados de Vendas'!D$2:D$151, E14, 'Dados de Vendas'!H$2:H$151) -> 66868.4
E15: Total | F15: =SUM(F10:F14) -> 237179.7

Sheet Dados de Vendas
A1: IDPedido | B1: Data | C1: Canal de Venda | D1: Região | E1: Modelo de Ventilador | F1: Preço Unitário | G1: Quantidade | H1: Faturamento | I1: Custo do Produto | J1: Margem Lucro
A2: REQ0002 | B2: 45985 | C2: E-commerce | D2: Sudeste | E2: Ventilador de Teto Moderno | F2: 349.9 | G2: 4 | H2: =F2*G2 -> 1399.6 | I2: =165*G2 -> 660 | J2: =H2-I2 -> 739.6
A3: REQ0003 | B3: 45772 | C3: Lojas Físicas | D3: Sudeste | E3: Mini Ventilador USB | F3: 49.9 | G3: 2 | H3: =F3*G3 -> 99.8 | I3: =18*G3 -> 36 | J3: =H3-I3 -> 63.8
A4: REQ0004 | B4: 45960 | C4: Televendas | D4: Sudeste | E4: Ventilador de Mesa 30cm | F4: 149.9 | G4: 2 | H4: =F4*G4 -> 299.8 | I4: =75*G4 -> 150 | J4: =H4-I4 -> 149.8
A5: REQ0005 | B5: 45769 | C5: Lojas Físicas | D5: Norte | E5: Mini Ventilador USB | F5: 49.9 | G5: 1 | H5: =F5*G5 -> 49.9 | I5: =18*G5 -> 18 | J5: =H5-I5 -> 31.9
A6: REQ0006 | B6: 45945 | C6: Lojas Físicas | D6: Norte | E6: Circulador de Ar Turbo | F6: 249.9 | G6: 4 | H6: =F6*G6 -> 999.6 | I6: =120*G6 -> 480 | J6: =H6-I6 -> 519.6
A7: REQ0007 | B7: 45887 | C7: Marketplace | D7: Sudeste | E7: Ventilador de Coluna 40cm | F7: 199.9 | G7: 12 | H7: =F7*G7 -> 2398.8 | I7: =98*G7 -> 1176 | J7: =H7-I7 -> 1222.8
A8: REQ0008 | B8: 45874 | C8: Marketplace | D8: Sul | E8: Ventilador de Coluna 40cm | F8: 199.9 | G8: 4 | H8: =F8*G8 -> 799.6 | I8: =98*G8 -> 392 | J8: =H8-I8 -> 407.6
A9: REQ0009 | B9: 45830 | C9: E-commerce | D9: Sudeste | E9: Circulador de Ar Turbo | F9: 249.9 | G9: 2 | H9: =F9*G9 -> 499.8 | I9: =120*G9 -> 240 | J9: =H9-I9 -> 259.8
A10: REQ0010 | B10: 45841 | C10: Marketplace | D10: Norte | E10: Ventilador de Teto Moderno | F10: 349.9 | G10: 13 | H10: =F10*G10 -> 4548.7 | I10: =165*G10 -> 2145 | J10: =H10-I10 -> 2403.7
A11: REQ0011 | B11: 45680 | C11: Televendas | D11: Norte | E11: Ventilador de Mesa 30cm | F11: 149.9 | G11: 15 | H11: =F11*G11 -> 2248.5 | I11: =75*G11 -> 1125 | J11: =H11-I11 -> 1123.5
A12: REQ0012 | B12: 45851 | C12: E-commerce | D12: Norte | E12: Ventilador de Teto Moderno | F12: 349.9 | G12: 14 | H12: =F12*G12 -> 4898.6 | I12: =165*G12 -> 2310 | J12: =H12-I12 -> 2588.6
A13: REQ0013 | B13: 45979 | C13: Marketplace | D13: Norte | E13: Ventilador de Coluna 40cm | F13: 199.9 | G13: 12 | H13: =F13*G13 -> 2398.8 | I13: =98*G13 -> 1176 | J13: =H13-I13 -> 1222.8
A14: REQ0014 | B14: 45693 | C14: E-commerce | D14: Nordeste | E14: Ventilador de Teto Moderno | F14: 349.9 | G14: 2 | H14: =F14*G14 -> 699.8 | I14: =165*G14 -> 330 | J14: =H14-I14 -> 369.8
A15: REQ0015 | B15: 45777 | C15: E-commerce | D15: Centro-Oeste | E15: Ventilador de Teto Moderno | F15: 349.9 | G15: 8 | H15: =F15*G15 -> 2799.2 | I15: =165*G15 -> 1320 | J15: =H15-I15 -> 1479.2
A16: REQ0016 | B16: 45983 | C16: Marketplace | D16: Nordeste | E16: Ventilador de Teto Moderno | F16: 349.9 | G16: 6 | H16: =F16*G16 -> 2099.4 | I16: =165*G16 -> 990 | J16: =H16-I16 -> 1109.4
A17: REQ0017 | B17: 45765 | C17: Marketplace | D17: Sudeste | E17: Mini Ventilador USB | F17: 49.9 | G17: 11 | H17: =F17*G17 -> 548.9 | I17: =18*G17 -> 198 | J17: =H17-I17 -> 350.9
A18: REQ0018 | B18: 45745 | C18: Lojas Físicas | D18: Nordeste | E18: Circulador de Ar Turbo | F18: 249.9 | G18: 7 | H18: =F18*G18 -> 1749.3 | I18: =120*G18 -> 840 | J18: =H18-I18 -> 909.3
A19: REQ0019 | B19: 45796 | C19: Lojas Físicas | D19: Sul | E19: Ventilador de Mesa 30cm | F19: 149.9 | G19: 4 | H19: =F19*G19 -> 599.6 | I19: =75*G19 -> 300 | J19: =H19-I19 -> 299.6
A20: REQ0020 | B20: 45674 | C20: Marketplace | D20: Centro-Oeste | E20: Ventilador de Teto Moderno | F20: 349.9 | G20: 2 | H20: =F20*G20 -> 699.8 | I20: =165*G20 -> 330 | J20: =H20-I20 -> 369.8
A21: REQ0021 | B21: 45766 | C21: Marketplace | D21: Nordeste | E21: Circulador de Ar Turbo | F21: 249.9 | G21: 7 | H21: =F21*G21 -> 1749.3 | I21: =120*G21 -> 840 | J21: =H21-I21 -> 909.3
A22: REQ0022 | B22: 45987 | C22: Televendas | D22: Nordeste | E22: Ventilador de Teto Moderno | F22: 349.9 | G22: 3 | H22: =F22*G22 -> 1049.7 | I22: =165*G22 -> 495 | J22: =H22-I22 -> 554.7
A23: REQ0023 | B23: 45784 | C23: Marketplace | D23: Norte | E23: Circulador de Ar Turbo | F23: 249.9 | G23: 15 | H23: =F23*G23 -> 3748.5 | I23: =120*G23 -> 1800 | J23: =H23-I23 -> 1948.5
A24: REQ0024 | B24: 45956 | C24: Televendas | D24: Sul | E24: Ventilador de Coluna 40cm | F24: 199.9 | G24: 3 | H24: =F24*G24 -> 599.7 | I24: =98*G24 -> 294 | J24: =H24-I24 -> 305.7
A25: REQ0025 | B25: 45918 | C25: Televendas | D25: Sudeste | E25: Ventilador de Mesa 30cm | F25: 149.9 | G25: 14 | H25: =F25*G25 -> 2098.6 | I25: =75*G25 -> 1050 | J25: =H25-I25 -> 1048.6
A26: REQ0026 | B26: 45714 | C26: Lojas Físicas | D26: Nordeste | E26: Circulador de Ar Turbo | F26: 249.9 | G26: 10 | H26: =F26*G26 -> 2499 | I26: =120*G26 -> 1200 | J26: =H26-I26 -> 1299
A27: REQ0027 | B27: 45690 | C27: Televendas | D27: Centro-Oeste | E27: Mini Ventilador USB | F27: 49.9 | G27: 8 | H27: =F27*G27 -> 399.2 | I27: =18*G27 -> 144 | J27: =H27-I27 -> 255.2
A28: REQ0028 | B28: 45928 | C28: Marketplace | D28: Norte | E28: Ventilador de Mesa 30cm | F28: 149.9 | G28: 11 | H28: =F28*G28 -> 1648.9 | I28: =75*G28 -> 825 | J28: =H28-I28 -> 823.9
A29: REQ0029 | B29: 45716 | C29: Marketplace | D29: Sul | E29: Ventilador de Mesa 30cm | F29: 149.9 | G29: 5 | H29: =F29*G29 -> 749.5 | I29: =75*G29 -> 375 | J29: =H29-I29 -> 374.5
A30: REQ0030 | B30: 45880 | C30: Lojas Físicas | D30: Centro-Oeste | E30: Ventilador de Mesa 30cm | F30: 149.9 | G30: 12 | H30: =F30*G30 -> 1798.8 | I30: =75*G30 -> 900 | J30: =H30-I30 -> 898.8
A31: REQ0031 | B31: 45792 | C31: Lojas Físicas | D31: Norte | E31: Ventilador de Mesa 30cm | F31: 149.9 | G31: 14 | H31: =F31*G31 -> 2098.6 | I31: =75*G31 -> 1050 | J31: =H31-I31 -> 1048.6
A32: REQ0032 | B32: 45978 | C32: Marketplace | D32: Norte | E32: Mini Ventilador USB | F32: 49.9 | G32: 4 | H32: =F32*G32 -> 199.6 | I32: =18*G32 -> 72 | J32: =H32-I32 -> 127.6
A33: REQ0033 | B33: 45736 | C33: Marketplace | D33: Nordeste | E33: Mini Ventilador USB | F33: 49.9 | G33: 13 | H33: =F33*G33 -> 648.7 | I33: =18*G33 -> 234 | J33: =H33-I33 -> 414.7
A34: REQ0034 | B34: 45929 | C34: E-commerce | D34: Norte | E34: Ventilador de Teto Moderno | F34: 349.9 | G34: 8 | H34: =F34*G34 -> 2799.2 | I34: =165*G34 -> 1320 | J34: =H34-I34 -> 1479.2
A35: REQ0035 | B35: 45667 | C35: E-commerce | D35: Sul | E35: Ventilador de Teto Moderno | F35: 349.9 | G35: 4 | H35: =F35*G35 -> 1399.6 | I35: =165*G35 -> 660 | J35: =H35-I35 -> 739.6
A36: REQ0036 | B36: 45687 | C36: Lojas Físicas | D36: Norte | E36: Ventilador de Mesa 30cm | F36: 149.9 | G36: 2 | H36: =F36*G36 -> 299.8 | I36: =75*G36 -> 150 | J36: =H36-I36 -> 149.8
A37: REQ0037 | B37: 45906 | C37: E-commerce | D37: Norte | E37: Ventilador de Coluna 40cm | F37: 199.9 | G37: 3 | H37: =F37*G37 -> 599.7 | I37: =98*G37 -> 294 | J37: =H37-I37 -> 305.7
A38: REQ0038 | B38: 45995 | C38: Televendas | D38: Norte | E38: Ventilador de Coluna 40cm | F38: 199.9 | G38: 5 | H38: =F38*G38 -> 999.5 | I38: =98*G38 -> 490 | J38: =H38-I38 -> 509.5
A39: REQ0039 | B39: 45928 | C39: Televendas | D39: Nordeste | E39: Mini Ventilador USB | F39: 49.9 | G39: 13 | H39: =F39*G39 -> 648.7 | I39: =18*G39 -> 234 | J39: =H39-I39 -> 414.7
A40: REQ0040 | B40: 46011 | C40: Lojas Físicas | D40: Sul | E40: Circulador de Ar Turbo | F40: 249.9 | G40: 11 | H40: =F40*G40 -> 2748.9 | I40: =120*G40 -> 1320 | J40: =H40-I40 -> 1428.9
A41: REQ0041 | B41: 45990 | C41: Marketplace | D41: Centro-Oeste | E41: Mini Ventilador USB | F41: 49.9 | G41: 8 | H41: =F41*G41 -> 399.2 | I41: =18*G41 -> 144 | J41: =H41-I41 -> 255.2
A42: REQ0042 | B42: 45719 | C42: Lojas Físicas | D42: Nordeste | E42: Ventilador de Mesa 30cm | F42: 149.9 | G42: 6 | H42: =F42*G42 -> 899.4 | I42: =75*G42 -> 450 | J42: =H42-I42 -> 449.4
A43: REQ0043 | B43: 45668 | C43: Lojas Físicas | D43: Norte | E43: Ventilador de Coluna 40cm | F43: 199.9 | G43: 1 | H43: =F43*G43 -> 199.9 | I43: =98*G43 -> 98 | J43: =H43-I43 -> 101.9
A44: REQ0044 | B44: 45694 | C44: E-commerce | D44: Nordeste | E44: Ventilador de Mesa 30cm | F44: 149.9 | G44: 15 | H44: =F44*G44 -> 2248.5 | I44: =75*G44 -> 1125 | J44: =H44-I44 -> 1123.5
A45: REQ0045 | B45: 45674 | C45: Marketplace | D45: Sudeste | E45: Mini Ventilador USB | F45: 49.9 | G45: 4 | H45: =F45*G45 -> 199.6 | I45: =18*G45 -> 72 | J45: =H45-I45 -> 127.6
A46: REQ0046 | B46: 45800 | C46: Televendas | D46: Nordeste | E46: Mini Ventilador USB | F46: 49.9 | G46: 3 | H46: =F46*G46 -> 149.7 | I46: =18*G46 -> 54 | J46: =H46-I46 -> 95.7
A47: REQ0047 | B47: 45950 | C47: Televendas | D47: Nordeste | E47: Circulador de Ar Turbo | F47: 249.9 | G47: 13 | H47: =F47*G47 -> 3248.7 | I47: =120*G47 -> 1560 | J47: =H47-I47 -> 1688.7
A48: REQ0048 | B48: 45866 | C48: Lojas Físicas | D48: Sudeste | E48: Ventilador de Mesa 30cm | F48: 149.9 | G48: 11 | H48: =F48*G48 -> 1648.9 | I48: =75*G48 -> 825 | J48: =H48-I48 -> 823.9
A49: REQ0049 | B49: 45878 | C49: Marketplace | D49: Centro-Oeste | E49: Circulador de Ar Turbo | F49: 249.9 | G49: 8 | H49: =F49*G49 -> 1999.2 | I49: =120*G49 -> 960 | J49: =H49-I49 -> 1039.2
A50: REQ0050 | B50: 45685 | C50: E-commerce | D50: Sudeste | E50: Circulador de Ar Turbo | F50: 249.9 | G50: 12 | H50: =F50*G50 -> 2998.8 | I50: =120*G50 -> 1440 | J50: =H50-I50 -> 1558.8
A51: REQ0051 | B51: 45831 | C51: E-commerce | D51: Nordeste | E51: Ventilador de Coluna 40cm | F51: 199.9 | G51: 4 | H51: =F51*G51 -> 799.6 | I51: =98*G51 -> 392 | J51: =H51-I51 -> 407.6
A52: REQ0052 | B52: 45932 | C52: Televendas | D52: Nordeste | E52: Circulador de Ar Turbo | F52: 249.9 | G52: 3 | H52: =F52*G52 -> 749.7 | I52: =120*G52 -> 360 | J52: =H52-I52 -> 389.7
A53: REQ0053 | B53: 45800 | C53: Televendas | D53: Nordeste | E53: Ventilador de Mesa 30cm | F53: 149.9 | G53: 8 | H53: =F53*G53 -> 1199.2 | I53: =75*G53 -> 600 | J53: =H53-I53 -> 599.2
A54: REQ0054 | B54: 45939 | C54: E-commerce | D54: Sudeste | E54: Mini Ventilador USB | F54: 49.9 | G54: 14 | H54: =F54*G54 -> 698.6 | I54: =18*G54 -> 252 | J54: =H54-I54 -> 446.6
A55: REQ0055 | B55: 45665 | C55: E-commerce | D55: Nordeste | E55: Ventilador de Coluna 40cm | F55: 199.9 | G55: 7 | H55: =F55*G55 -> 1399.3 | I55: =98*G55 -> 686 | J55: =H55-I55 -> 713.3
A56: REQ0056 | B56: 45906 | C56: Televendas | D56: Nordeste | E56: Circulador de Ar Turbo | F56: 249.9 | G56: 15 | H56: =F56*G56 -> 3748.5 | I56: =120*G56 -> 1800 | J56: =H56-I56 -> 1948.5
A57: REQ0057 | B57: 45688 | C57: Lojas Físicas | D57: Centro-Oeste | E57: Ventilador de Mesa 30cm | F57: 149.9 | G57: 7 | H57: =F57*G57 -> 1049.3 | I57: =75*G57 -> 525 | J57: =H57-I57 -> 524.3
A58: REQ0058 | B58: 45793 | C58: Televendas | D58: Sul | E58: Circulador de Ar Turbo | F58: 249.9 | G58: 12 | H58: =F58*G58 -> 2998.8 | I58: =120*G58 -> 1440 | J58: =H58-I58 -> 1558.8
A59: REQ0059 | B59: 45942 | C59: Televendas | D59: Nordeste | E59: Ventilador de Coluna 40cm | F59: 199.9 | G59: 5 | H59: =F59*G59 -> 999.5 | I59: =98*G59 -> 490 | J59: =H59-I59 -> 509.5
A60: REQ0060 | B60: 45769 | C60: E-commerce | D60: Norte | E60: Mini Ventilador USB | F60: 49.9 | G60: 1 | H60: =F60*G60 -> 49.9 | I60: =18*G60 -> 18 | J60: =H60-I60 -> 31.9
A61: REQ0061 | B61: 45818 | C61: E-commerce | D61: Sudeste | E61: Mini Ventilador USB | F61: 49.9 | G61: 8 | H61: =F61*G61 -> 399.2 | I61: =18*G61 -> 144 | J61: =H61-I61 -> 255.2
A62: REQ0062 | B62: 45915 | C62: Lojas Físicas | D62: Sudeste | E62: Mini Ventilador USB | F62: 49.9 | G62: 2 | H62: =F62*G62 -> 99.8 | I62: =18*G62 -> 36 | J62: =H62-I62 -> 63.8
A63: REQ0063 | B63: 45753 | C63: E-commerce | D63: Norte | E63: Ventilador de Mesa 30cm | F63: 149.9 | G63: 11 | H63: =F63*G63 -> 1648.9 | I63: =75*G63 -> 825 | J63: =H63-I63 -> 823.9
A64: REQ0064 | B64: 45778 | C64: Televendas | D64: Sudeste | E64: Mini Ventilador USB | F64: 49.9 | G64: 4 | H64: =F64*G64 -> 199.6 | I64: =18*G64 -> 72 | J64: =H64-I64 -> 127.6
A65: REQ0065 | B65: 45954 | C65: E-commerce | D65: Norte | E65: Ventilador de Mesa 30cm | F65: 149.9 | G65: 7 | H65: =F65*G65 -> 1049.3 | I65: =75*G65 -> 525 | J65: =H65-I65 -> 524.3
A66: REQ0066 | B66: 45994 | C66: Marketplace | D66: Sul | E66: Ventilador de Coluna 40cm | F66: 199.9 | G66: 11 | H66: =F66*G66 -> 2198.9 | I66: =98*G66 -> 1078 | J66: =H66-I66 -> 1120.9
A67: REQ0067 | B67: 45818 | C67: Lojas Físicas | D67: Sul | E67: Circulador de Ar Turbo | F67: 249.9 | G67: 3 | H67: =F67*G67 -> 749.7 | I67: =120*G67 -> 360 | J67: =H67-I67 -> 389.7
A68: REQ0068 | B68: 46001 | C68: Marketplace | D68: Centro-Oeste | E68: Ventilador de Teto Moderno | F68: 349.9 | G68: 15 | H68: =F68*G68 -> 5248.5 | I68: =165*G68 -> 2475 | J68: =H68-I68 -> 2773.5
A69: REQ0069 | B69: 45695 | C69: E-commerce | D69: Centro-Oeste | E69: Mini Ventilador USB | F69: 49.9 | G69: 10 | H69: =F69*G69 -> 499 | I69: =18*G69 -> 180 | J69: =H69-I69 -> 319
A70: REQ0070 | B70: 45709 | C70: E-commerce | D70: Norte | E70: Ventilador de Coluna 40cm | F70: 199.9 | G70: 9 | H70: =F70*G70 -> 1799.1 | I70: =98*G70 -> 882 | J70: =H70-I70 -> 917.1
A71: REQ0071 | B71: 45793 | C71: Lojas Físicas | D71: Sul | E71: Ventilador de Mesa 30cm | F71: 149.9 | G71: 15 | H71: =F71*G71 -> 2248.5 | I71: =75*G71 -> 1125 | J71: =H71-I71 -> 1123.5
A72: REQ0072 | B72: 45783 | C72: Marketplace | D72: Sul | E72: Ventilador de Coluna 40cm | F72: 199.9 | G72: 8 | H72: =F72*G72 -> 1599.2 | I72: =98*G72 -> 784 | J72: =H72-I72 -> 815.2
A73: REQ0073 | B73: 45936 | C73: Marketplace | D73: Norte | E73: Mini Ventilador USB | F73: 49.9 | G73: 1 | H73: =F73*G73 -> 49.9 | I73: =18*G73 -> 18 | J73: =H73-I73 -> 31.9
A74: REQ0074 | B74: 45999 | C74: Marketplace | D74: Sudeste | E74: Ventilador de Coluna 40cm | F74: 199.9 | G74: 5 | H74: =F74*G74 -> 999.5 | I74: =98*G74 -> 490 | J74: =H74-I74 -> 509.5
A75: REQ0075 | B75: 45717 | C75: E-commerce | D75: Norte | E75: Ventilador de Coluna 40cm | F75: 199.9 | G75: 5 | H75: =F75*G75 -> 999.5 | I75: =98*G75 -> 490 | J75: =H75-I75 -> 509.5
A76: REQ0076 | B76: 45802 | C76: Lojas Físicas | D76: Sul | E76: Ventilador de Coluna 40cm | F76: 199.9 | G76: 11 | H76: =F76*G76 -> 2198.9 | I76: =98*G76 -> 1078 | J76: =H76-I76 -> 1120.9
A77: REQ0077 | B77: 45982 | C77: Marketplace | D77: Norte | E77: Circulador de Ar Turbo | F77: 249.9 | G77: 5 | H77: =F77*G77 -> 1249.5 | I77: =120*G77 -> 600 | J77: =H77-I77 -> 649.5
A78: REQ0078 | B78: 45684 | C78: E-commerce | D78: Centro-Oeste | E78: Ventilador de Teto Moderno | F78: 349.9 | G78: 1 | H78: =F78*G78 -> 349.9 | I78: =165*G78 -> 165 | J78: =H78-I78 -> 184.9
A79: REQ0079 | B79: 45659 | C79: Marketplace | D79: Nordeste | E79: Ventilador de Teto Moderno | F79: 349.9 | G79: 3 | H79: =F79*G79 -> 1049.7 | I79: =165*G79 -> 495 | J79: =H79-I79 -> 554.7
A80: REQ0080 | B80: 45884 | C80: Televendas | D80: Norte | E80: Ventilador de Mesa 30cm | F80: 149.9 | G80: 2 | H80: =F80*G80 -> 299.8 | I80: =75*G80 -> 150 | J80: =H80-I80 -> 149.8
A81: REQ0081 | B81: 45696 | C81: Lojas Físicas | D81: Norte | E81: Ventilador de Mesa 30cm | F81: 149.9 | G81: 14 | H81: =F81*G81 -> 2098.6 | I81: =75*G81 -> 1050 | J81: =H81-I81 -> 1048.6
A82: REQ0082 | B82: 45847 | C82: Lojas Físicas | D82: Centro-Oeste | E82: Ventilador de Coluna 40cm | F82: 199.9 | G82: 1 | H82: =F82*G82 -> 199.9 | I82: =98*G82 -> 98 | J82: =H82-I82 -> 101.9
A83: REQ0083 | B83: 45815 | C83: Marketplace | D83: Sudeste | E83: Ventilador de Teto Moderno | F83: 349.9 | G83: 4 | H83: =F83*G83 -> 1399.6 | I83: =165*G83 -> 660 | J83: =H83-I83 -> 739.6
A84: REQ0084 | B84: 46007 | C84: Lojas Físicas | D84: Sudeste | E84: Ventilador de Teto Moderno | F84: 349.9 | G84: 13 | H84: =F84*G84 -> 4548.7 | I84: =165*G84 -> 2145 | J84: =H84-I84 -> 2403.7
A85: REQ0085 | B85: 45944 | C85: Televendas | D85: Norte | E85: Ventilador de Coluna 40cm | F85: 199.9 | G85: 15 | H85: =F85*G85 -> 2998.5 | I85: =98*G85 -> 1470 | J85: =H85-I85 -> 1528.5
A86: REQ0086 | B86: 45779 | C86: Lojas Físicas | D86: Nordeste | E86: Circulador de Ar Turbo | F86: 249.9 | G86: 1 | H86: =F86*G86 -> 249.9 | I86: =120*G86 -> 120 | J86: =H86-I86 -> 129.9
A87: REQ0087 | B87: 45749 | C87: Marketplace | D87: Centro-Oeste | E87: Ventilador de Coluna 40cm | F87: 199.9 | G87: 5 | H87: =F87*G87 -> 999.5 | I87: =98*G87 -> 490 | J87: =H87-I87 -> 509.5
A88: REQ0088 | B88: 45739 | C88: E-commerce | D88: Centro-Oeste | E88: Ventilador de Mesa 30cm | F88: 149.9 | G88: 14 | H88: =F88*G88 -> 2098.6 | I88: =75*G88 -> 1050 | J88: =H88-I88 -> 1048.6
A89: REQ0089 | B89: 45898 | C89: Lojas Físicas | D89: Nordeste | E89: Circulador de Ar Turbo | F89: 249.9 | G89: 6 | H89: =F89*G89 -> 1499.4 | I89: =120*G89 -> 720 | J89: =H89-I89 -> 779.4
A90: REQ0090 | B90: 45814 | C90: Lojas Físicas | D90: Nordeste | E90: Ventilador de Mesa 30cm | F90: 149.9 | G90: 11 | H90: =F90*G90 -> 1648.9 | I90: =75*G90 -> 825 | J90: =H90-I90 -> 823.9
A91: REQ0091 | B91: 45756 | C91: Televendas | D91: Sul | E91: Ventilador de Teto Moderno | F91: 349.9 | G91: 14 | H91: =F91*G91 -> 4898.6 | I91: =165*G91 -> 2310 | J91: =H91-I91 -> 2588.6
A92: REQ0092 | B92: 45693 | C92: Marketplace | D92: Sul | E92: Mini Ventilador USB | F92: 49.9 | G92: 7 | H92: =F92*G92 -> 349.3 | I92: =18*G92 -> 126 | J92: =H92-I92 -> 223.3
A93: REQ0093 | B93: 46005 | C93: Marketplace | D93: Sudeste | E93: Ventilador de Mesa 30cm | F93: 149.9 | G93: 15 | H93: =F93*G93 -> 2248.5 | I93: =75*G93 -> 1125 | J93: =H93-I93 -> 1123.5
A94: REQ0094 | B94: 45791 | C94: Lojas Físicas | D94: Norte | E94: Ventilador de Teto Moderno | F94: 349.9 | G94: 1 | H94: =F94*G94 -> 349.9 | I94: =165*G94 -> 165 | J94: =H94-I94 -> 184.9
A95: REQ0095 | B95: 45713 | C95: Televendas | D95: Sul | E95: Ventilador de Teto Moderno | F95: 349.9 | G95: 7 | H95: =F95*G95 -> 2449.3 | I95: =165*G95 -> 1155 | J95: =H95-I95 -> 1294.3
A96: REQ0096 | B96: 45968 | C96: E-commerce | D96: Centro-Oeste | E96: Mini Ventilador USB | F96: 49.9 | G96: 4 | H96: =F96*G96 -> 199.6 | I96: =18*G96 -> 72 | J96: =H96-I96 -> 127.6
A97: REQ0097 | B97: 45788 | C97: E-commerce | D97: Centro-Oeste | E97: Ventilador de Mesa 30cm | F97: 149.9 | G97: 9 | H97: =F97*G97 -> 1349.1 | I97: =75*G97 -> 675 | J97: =H97-I97 -> 674.1
A98: REQ0098 | B98: 45933 | C98: Lojas Físicas | D98: Sul | E98: Circulador de Ar Turbo | F98: 249.9 | G98: 2 | H98: =F98*G98 -> 499.8 | I98: =120*G98 -> 240 | J98: =H98-I98 -> 259.8
A99: REQ0099 | B99: 45998 | C99: Marketplace | D99: Norte | E99: Ventilador de Teto Moderno | F99: 349.9 | G99: 11 | H99: =F99*G99 -> 3848.9 | I99: =165*G99 -> 1815 | J99: =H99-I99 -> 2033.9
A100: REQ0100 | B100: 45721 | C100: Marketplace | D100: Norte | E100: Ventilador de Teto Moderno | F100: 349.9 | G100: 11 | H100: =F100*G100 -> 3848.9 | I100: =165*G100 -> 1815 | J100: =H100-I100 -> 2033.9
...
